chanjet_openapi_python_sdk/__init__.py
chanjet_openapi_python_sdk/chanjet_client.py
chanjet_openapi_python_sdk/chanjet_content.py
chanjet_openapi_python_sdk/chanjet_request.py
chanjet_openapi_python_sdk/chanjet_response.py
chanjet_openapi_python_sdk/common_api_demo.py
chanjet_openapi_python_sdk/tplus_api_demo.py
chanjet_openapi_python_sdk/content/__init__.py
chanjet_openapi_python_sdk/content/add_user_content.py
chanjet_openapi_python_sdk/content/create_order_content.py
chanjet_openapi_python_sdk/content/create_tenant_content.py
chanjet_openapi_python_sdk/content/get_app_access_token_content.py
chanjet_openapi_python_sdk/content/get_org_access_token_content.py
chanjet_openapi_python_sdk/content/get_permanent_auth_code_content.py
chanjet_openapi_python_sdk/content/get_tenant_token_content.py
chanjet_openapi_python_sdk/content/get_token_by_permanent_code_content.py
chanjet_openapi_python_sdk/content/get_user_token_content.py
chanjet_openapi_python_sdk/content/refresh_token_content.py
chanjet_openapi_python_sdk/content/remove_user_content.py
chanjet_openapi_python_sdk/content/trail_product_content.py
chanjet_openapi_python_sdk/content/tplus/__init__.py
chanjet_openapi_python_sdk/content/tplus/create_doc_content.py
chanjet_openapi_python_sdk/content/tplus/create_inventory_content.py
chanjet_openapi_python_sdk/content/tplus/create_partner_content.py
chanjet_openapi_python_sdk/content/tplus/create_sale_delivery_contect.py
chanjet_openapi_python_sdk/content/tplus/create_sale_order_content.py
chanjet_openapi_python_sdk/content/tplus/query_current_stock_content.py
chanjet_openapi_python_sdk/content/tplus/query_inventory_content.py
chanjet_openapi_python_sdk/content/tplus/query_partner_content.py
chanjet_openapi_python_sdk/content/tplus/query_report_data_content.py
chanjet_openapi_python_sdk/exception/__init__.py
chanjet_openapi_python_sdk/exception/http_method_exception.py
chanjet_openapi_python_sdk/exception/serialize_response_exception.py
chanjet_openapi_python_sdk-1.0.2.dist-info/LICENSE
chanjet_openapi_python_sdk-1.0.2.dist-info/METADATA
chanjet_openapi_python_sdk-1.0.2.dist-info/WHEEL
chanjet_openapi_python_sdk-1.0.2.dist-info/top_level.txt
chanjet_openapi_python_sdk-1.0.2.dist-info/RECORD
