Metadata-Version: 2.1
Name: chanjet-openapi-python-sdk
Version: 1.0.2
Summary: 畅捷通开放平台python版sdk
Home-page: https://github.com/Chanjet/chanjet-openapi-python-sdk
Author: zc
Author-email: zhaochang1@chanjet.com
License: MIT
Platform: UNKNOWN
Classifier: Programming Language :: Python :: 3.8
Classifier: License :: OSI Approved :: MIT License
Classifier: Operating System :: OS Independent
License-File: LICENSE
Requires-Dist: requests (==2.26.0)
